poseur.py
bpc_poseur-0.4.3.post1.dist-info/LICENSE
bpc_poseur-0.4.3.post1.dist-info/METADATA
bpc_poseur-0.4.3.post1.dist-info/WHEEL
bpc_poseur-0.4.3.post1.dist-info/entry_points.txt
bpc_poseur-0.4.3.post1.dist-info/top_level.txt
bpc_poseur-0.4.3.post1.dist-info/RECORD
