Metadata-Version: 2.1
Name: bpc-poseur
Version: 0.4.3.post1
Summary: Back-port compiler for Python 3.8 positional-only parameter syntax.
Home-page: https://github.com/pybpc/poseur
Author: Jarry Shaw
Author-email: jarryshaw@icloud.com
License: MIT
Keywords: positional-only parameters,back-port compiler
Classifier: Development Status :: 5 - Production/Stable
Classifier: Intended Audience :: Developers
Classifier: Intended Audience :: Information Technology
Classifier: License :: OSI Approved :: MIT License
Classifier: Operating System :: OS Independent
Classifier: Programming Language :: Python :: 3.4
Classifier: Programming Language :: Python :: 3.5
Classifier: Programming Language :: Python :: 3.6
Classifier: Programming Language :: Python :: 3.7
Classifier: Programming Language :: Python :: 3.8
Classifier: Programming Language :: Python :: 3.9
Classifier: Programming Language :: Python :: 3 :: Only
Classifier: Topic :: Software Development
Classifier: Topic :: Utilities
Classifier: Typing :: Typed
Requires-Python: >=3.4
License-File: LICENSE
Requires-Dist: parso (~=0.6.0)
Requires-Dist: tbtrim (>=0.2.1)
Requires-Dist: bpc-f2format
Requires-Dist: bpc-utils (~=0.10.0)
Requires-Dist: typing-extensions
Requires-Dist: typing ; python_version < "3.5"
Provides-Extra: docs
Requires-Dist: Sphinx ; extra == 'docs'
Requires-Dist: sphinx-autodoc-typehints ; extra == 'docs'
Requires-Dist: sphinxemoji ; extra == 'docs'
Provides-Extra: lint
Requires-Dist: flake8 ; extra == 'lint'
Requires-Dist: pylint ; extra == 'lint'
Requires-Dist: mypy ; extra == 'lint'
Requires-Dist: bandit (>=1.6.3) ; extra == 'lint'
Requires-Dist: vermin (>=1.1.0) ; extra == 'lint'
Requires-Dist: colorlabels (>=0.7.0) ; extra == 'lint'
Requires-Dist: parso (>=0.8.0) ; extra == 'lint'
Provides-Extra: test
Requires-Dist: pytest (>=4.5.0) ; extra == 'test'
Requires-Dist: pytest-doctestplus (>=0.5.0) ; extra == 'test'
Requires-Dist: coverage ; extra == 'test'
